dqoai/__init__.py
dqoai/install.py
dqoai/startdqo.py
dqoai/version.py
dqoai-0.1.0.1.dist-info/LICENSE
dqoai-0.1.0.1.dist-info/METADATA
dqoai-0.1.0.1.dist-info/WHEEL
dqoai-0.1.0.1.dist-info/entry_points.txt
dqoai-0.1.0.1.dist-info/top_level.txt
dqoai-0.1.0.1.dist-info/RECORD
